devious_pypsrp-1.0.1.dist-info/licenses/LICENSE
psrp/__init__.py
psrp/_async.py
psrp/_client.py
psrp/_exceptions.py
psrp/_host.py
psrp/_sync.py
psrp/_winrs.py
psrp/_wsman.py
psrp/py.typed
psrp/_connection/__init__.py
psrp/_connection/_win32.py
psrp/_connection/connection.py
psrp/_connection/named_pipe.py
psrp/_connection/out_of_proc.py
psrp/_connection/process.py
psrp/_connection/ssh.py
psrp/_connection/wsman.py
psrp/_io/__init__.py
psrp/_io/wsman.py
psrp/_pwsh/__init__.py
psrp/_pwsh/copy.ps1
psrp/_pwsh/fetch.ps1
pypsrp/__init__.py
pypsrp/_utils.py
pypsrp/client.py
pypsrp/complex_objects.py
pypsrp/encryption.py
pypsrp/exceptions.py
pypsrp/host.py
pypsrp/messages.py
pypsrp/negotiate.py
pypsrp/powershell.py
pypsrp/py.typed
pypsrp/serializer.py
pypsrp/shell.py
pypsrp/wsman.py
pypsrp/pwsh_scripts/__init__.py
pypsrp/pwsh_scripts/copy.ps1
pypsrp/pwsh_scripts/fetch.ps1
devious_pypsrp-1.0.1.dist-info/METADATA
devious_pypsrp-1.0.1.dist-info/WHEEL
devious_pypsrp-1.0.1.dist-info/top_level.txt
devious_pypsrp-1.0.1.dist-info/RECORD
