Metadata-Version: 2.4
Name: devious-pypsrp
Version: 1.0.1
Summary: pypsrp for use with Devious-WinRM
Author-email: Jordan Borean <jborean93@gmail.com>
License: MIT License
Project-URL: homepage, https://github.com/jborean93/pypsrp
Keywords: winrm,psrp,winrs,windows,powershell
Classifier: Development Status :: 4 - Beta
Classifier: License :: OSI Approved :: MIT License
Classifier: Programming Language :: Python :: 3
Classifier: Programming Language :: Python :: 3.8
Classifier: Programming Language :: Python :: 3.9
Classifier: Programming Language :: Python :: 3.10
Classifier: Programming Language :: Python :: 3.11
Requires-Python: >=3.8
License-File: LICENSE
Requires-Dist: cryptography
Requires-Dist: httpcore<1.0.0
Requires-Dist: httpx<1.0.0
Requires-Dist: psrpcore>=0.1.2
Requires-Dist: pyspnego<1.0.0,>=0.7.0
Requires-Dist: requests>=2.9.1
Provides-Extra: credssp
Requires-Dist: requests-credssp>=2.0.0; extra == "credssp"
Provides-Extra: kerberos
Requires-Dist: pyspnego[kerberos]; extra == "kerberos"
Provides-Extra: named-pipe
Requires-Dist: psutil; extra == "named-pipe"
Provides-Extra: ssh
Requires-Dist: asyncssh; extra == "ssh"
Dynamic: license-file
